CHANGES.txt
COPYRIGHT.txt
LICENSE.txt
README.txt
setup.cfg
setup.py
repoze/__init__.py
repoze.bfg.viewgroup.egg-info/PKG-INFO
repoze.bfg.viewgroup.egg-info/SOURCES.txt
repoze.bfg.viewgroup.egg-info/dependency_links.txt
repoze.bfg.viewgroup.egg-info/entry_points.txt
repoze.bfg.viewgroup.egg-info/namespace_packages.txt
repoze.bfg.viewgroup.egg-info/not-zip-safe
repoze.bfg.viewgroup.egg-info/requires.txt
repoze.bfg.viewgroup.egg-info/top_level.txt
repoze/bfg/__init__.py
repoze/bfg/viewgroup/__init__.py
repoze/bfg/viewgroup/group.py
repoze/bfg/viewgroup/meta.zcml
repoze/bfg/viewgroup/zcml.py
repoze/bfg/viewgroup/tests/__init__.py
repoze/bfg/viewgroup/tests/test_all.py
repoze/bfg/viewgroup/tests/fixtureapp/__init__.py
repoze/bfg/viewgroup/tests/fixtureapp/another.zcml
repoze/bfg/viewgroup/tests/fixtureapp/configure.zcml
repoze/bfg/viewgroup/tests/fixtureapp/models.py
repoze/bfg/viewgroup/tests/fixtureapp/views.py
repoze/bfg/viewgroup/tests/fixtureapp/templates/fixture.pt