Metadata-Version: 1.0
Name: repoze.bfg.viewgroup
Version: 0.3
Summary: An anlologue of Zope 3 "content providers" for repoze.bfg
Home-page: http://www.repoze.org
Author: Agendaless Consulting
Author-email: repoze-dev@lists.repoze.org
License: BSD-derived (http://www.repoze.org/LICENSE.txt)
Keywords: web wsgi zope content provider
Platform: UNKNOWN
Classifier: Intended Audience :: Developers
Classifier: Programming Language :: Python
Classifier: Framework :: BFG
